dtt2hdf/__init__.py
dtt2hdf/access.py
dtt2hdf/diag_clear.py
dtt2hdf/diag_run.py
dtt2hdf/dtt2hdf.py
dtt2hdf/framecpp_read.py
dtt2hdf/normalizer.py
dtt2hdf/parse.py
dtt2hdf/parse_coefficients.py
dtt2hdf/parse_spectrum.py
dtt2hdf/parse_timeseries.py
dtt2hdf/parse_transfer.py
dtt2hdf-1.0.0.dev1.dist-info/DESCRIPTION.rst
dtt2hdf-1.0.0.dev1.dist-info/METADATA
dtt2hdf-1.0.0.dev1.dist-info/RECORD
dtt2hdf-1.0.0.dev1.dist-info/WHEEL
dtt2hdf-1.0.0.dev1.dist-info/entry_points.txt
dtt2hdf-1.0.0.dev1.dist-info/metadata.json
dtt2hdf-1.0.0.dev1.dist-info/top_level.txt
