Metadata-Version: 2.0
Name: dtt2hdf
Version: 1.0.0.dev1
Summary: Extract data from LIGO Diagnostics test tools XML format.
Home-page: UNKNOWN
Author: Lee McCuller
Author-email: Lee.McCuller@ligo.org
License: Apache v2
Keywords: LIGO diagnostics file reader
Platform: UNKNOWN
Classifier: License :: OSI Approved :: Apache Software License
Classifier: Operating System :: OS Independent
Classifier: Programming Language :: Python
Classifier: Programming Language :: Python :: 2
Classifier: Programming Language :: Python :: 2.7
Classifier: Programming Language :: Python :: 3
Classifier: Programming Language :: Python :: 3.4
Classifier: Programming Language :: Python :: 3.5
Classifier: Programming Language :: Python :: 3.6
Classifier: Topic :: Software Development :: Libraries :: Python Modules
Requires-Dist: declarative[hdf]
